gitgo/__init__.py
gitgo/__main__.py
gitgo-1.0.6.dist-info/METADATA
gitgo-1.0.6.dist-info/WHEEL
gitgo-1.0.6.dist-info/entry_points.txt
gitgo-1.0.6.dist-info/top_level.txt
gitgo-1.0.6.dist-info/RECORD
