Metadata-Version: 2.4
Name: gitgo
Version: 1.0.6
Summary: A safe Git commit, versioning, and push helper with AI-assisted messages
Author: appfeat
License: MIT
Project-URL: Homepage, https://github.com/appfeat/gitgo
Project-URL: Repository, https://github.com/appfeat/gitgo
Project-URL: Issues, https://github.com/appfeat/gitgo/issues
Keywords: git,cli,commit,versioning,ai
Classifier: Programming Language :: Python :: 3
Classifier: Programming Language :: Python :: 3 :: Only
Classifier: License :: OSI Approved :: MIT License
Classifier: Environment :: Console
Classifier: Topic :: Software Development :: Version Control :: Git
Requires-Python: >=3.9
